{
  "parent": "minecraft:recipes/root",
  "criteria": {
    "has_plastic_orange": {
      "conditions": {
        "items": [
          {
            "items": [
              "avp:plastic_orange"
            ]
          }
        ]
      },
      "trigger": "minecraft:inventory_changed"
    },
    "has_the_recipe": {
      "conditions": {
        "recipe": "minecraft:plastic_orange_stairs_from_plastic_orange_stonecutting"
      },
      "trigger": "minecraft:recipe_unlocked"
    }
  },
  "requirements": [
    [
      "has_the_recipe",
      "has_plastic_orange"
    ]
  ],
  "rewards": {
    "recipes": [
      "minecraft:plastic_orange_stairs_from_plastic_orange_stonecutting"
    ]
  }
}